wagtail_crx_block_frontend_assets/__init__.py
wagtail_crx_block_frontend_assets/apps.py
wagtail_crx_block_frontend_assets/blocks.py
wagtail_crx_block_frontend_assets/wagtail_hooks.py
wagtail_crx_block_frontend_assets/templates/wagtail_crx_block_frontend_assets/includes/block_assets.html
wagtail_crx_block_frontend_assets/templatetags/__init__.py
wagtail_crx_block_frontend_assets/templatetags/block_assets_tags.py
wagtail_crx_block_frontend_assets-1.1.0.dist-info/licenses/LICENSE
wagtail_crx_block_frontend_assets-1.1.0.dist-info/METADATA
wagtail_crx_block_frontend_assets-1.1.0.dist-info/WHEEL
wagtail_crx_block_frontend_assets-1.1.0.dist-info/top_level.txt
wagtail_crx_block_frontend_assets-1.1.0.dist-info/RECORD
