Metadata-Version: 2.4
Name: wagtail_crx_block_frontend_assets
Version: 1.1.0
Summary: This package allows you to define and organise static assets for your Wagtail blocks frontend.
Author-email: Daniel Kunický <danecek37@gmail.com>
Project-URL: Homepage, https://github.com/LESPROJEKT/wagtail-crx-block-frontend-assets
Project-URL: Issues, https://github.com/LESPROJEKT/wagtail-crx-block-frontend-assets/issues
Classifier: Programming Language :: Python :: 3
Classifier: License :: OSI Approved :: MIT License
Classifier: Operating System :: OS Independent
Requires-Python: >=3.9
License-File: LICENSE
Requires-Dist: coderedcms<6,>=2.1
Requires-Dist: wagtail<7,>=4.2
Provides-Extra: test
Requires-Dist: pytest>=7.4; extra == "test"
Requires-Dist: pytest-django>=4.8; extra == "test"
Dynamic: license-file
